tb_paddle/__init__.py
tb_paddle/crc32c.py
tb_paddle/embedding.py
tb_paddle/event_file_loader.py
tb_paddle/event_file_writer.py
tb_paddle/file_writer.py
tb_paddle/hparams_api.py
tb_paddle/hparams_summary.py
tb_paddle/logger.py
tb_paddle/paddle_graph.py
tb_paddle/proto_graph.py
tb_paddle/record_reader.py
tb_paddle/record_writer.py
tb_paddle/summary.py
tb_paddle/summary_reader.py
tb_paddle/summary_writer.py
tb_paddle/utils.py
tb_paddle/x2num.py
tb_paddle/proto/__init__.py
tb_paddle/proto/api.proto
tb_paddle/proto/api_pb2.py
tb_paddle/proto/attr_value.proto
tb_paddle/proto/attr_value_pb2.py
tb_paddle/proto/event.proto
tb_paddle/proto/event_pb2.py
tb_paddle/proto/graph.proto
tb_paddle/proto/graph_pb2.py
tb_paddle/proto/layout.proto
tb_paddle/proto/layout_pb2.py
tb_paddle/proto/node_def.proto
tb_paddle/proto/node_def_pb2.py
tb_paddle/proto/plugin_data.proto
tb_paddle/proto/plugin_data_pb2.py
tb_paddle/proto/plugin_mesh.proto
tb_paddle/proto/plugin_mesh_pb2.py
tb_paddle/proto/plugin_pr_curve.proto
tb_paddle/proto/plugin_pr_curve_pb2.py
tb_paddle/proto/plugin_text.proto
tb_paddle/proto/plugin_text_pb2.py
tb_paddle/proto/resource_handle.proto
tb_paddle/proto/resource_handle_pb2.py
tb_paddle/proto/step_stats.proto
tb_paddle/proto/step_stats_pb2.py
tb_paddle/proto/summary.proto
tb_paddle/proto/summary_pb2.py
tb_paddle/proto/tensor.proto
tb_paddle/proto/tensor_pb2.py
tb_paddle/proto/tensor_shape.proto
tb_paddle/proto/tensor_shape_pb2.py
tb_paddle/proto/types.proto
tb_paddle/proto/types_pb2.py
tb_paddle/proto/versions.proto
tb_paddle/proto/versions_pb2.py
tb_paddle/proto/__pycache__/__init__.cpython-36.pyc
tb_paddle/proto/__pycache__/__init__.cpython-37.pyc
tb_paddle/proto/__pycache__/api_pb2.cpython-36.pyc
tb_paddle/proto/__pycache__/attr_value_pb2.cpython-36.pyc
tb_paddle/proto/__pycache__/event_pb2.cpython-36.pyc
tb_paddle/proto/__pycache__/event_pb2.cpython-37.pyc
tb_paddle/proto/__pycache__/graph_pb2.cpython-36.pyc
tb_paddle/proto/__pycache__/layout_pb2.cpython-36.pyc
tb_paddle-0.4.0.dist-info/LICENSE
tb_paddle-0.4.0.dist-info/METADATA
tb_paddle-0.4.0.dist-info/WHEEL
tb_paddle-0.4.0.dist-info/top_level.txt
tb_paddle-0.4.0.dist-info/RECORD
