Metadata-Version: 2.1
Name: tb-paddle
Version: 0.4.0
Summary: tb-paddle is a toolkit to visualize Paddle logged data in TensorBoard.
Home-page: https://github.com/linshuliang/tb-paddle
Author: ShuLiang Lin
Author-email: UNKNOWN
License: MIT license
Platform: UNKNOWN
Classifier: Intended Audience :: Developers
Classifier: License :: OSI Approved :: MIT License
Classifier: Natural Language :: English
Classifier: Programming Language :: Python :: 2
Classifier: Programming Language :: Python :: 2.7
Classifier: Programming Language :: Python :: 3
Classifier: Programming Language :: Python :: 3.5
Classifier: Programming Language :: Python :: 3.6
Requires-Dist: numpy
Requires-Dist: protobuf (>=3.6.1)
Requires-Dist: six
Requires-Dist: pillow
